{"type":"FeatureCollection","features":[{"type":"Feature","id":"way/416891069","properties":{"type":"way","id":416891069,"tags":{"addr:city":"Pokhara Lekhanath Metropolitan City","addr:place":"Santinagar","name":"Don Newspaper","name:ne":"डन पत्रिका","office":"newspaper","opening_hours":"24/7"},"relations":[],"meta":{"timestamp":"2018-06-21T05:10:46Z","version":6,"changeset":60029944,"user":"Ro Sun","uid":3112087}},"geometry":{"type":"Point","coordinates":[83.9729084,28.214286350000002]}},{"type":"Feature","id":"way/420987538","properties":{"type":"way","id":420987538,"tags":{"building":"yes","name":"Aadarsha Samaj","office":"newspaper"},"relations":[],"meta":{"timestamp":"2017-11-22T06:01:14Z","version":2,"changeset":53991893,"user":"nishaadhikari","uid":3481073}},"geometry":{"type":"Point","coordinates":[84.05637405,28.164358325]}},{"type":"Feature","id":"node/4182981254","properties":{"type":"node","id":4182981254,"tags":{"name":"Himdut Daily Press","name:ne":"हिमदुत डेली प्रेस","office":"newspaper"},"relations":[],"meta":{"timestamp":"2016-08-21T06:37:00Z","version":3,"changeset":41587595,"user":"Alisha12","uid":4204463}},"geometry":{"type":"Point","coordinates":[83.9904656,28.2187226]}},{"type":"Feature","id":"node/4191244528","properties":{"type":"node","id":4191244528,"tags":{"name":"Sarangkot Weekly Newspaper","name:ne":"सारंगकोट विक्ली न्युज-पेपर","office":"newspaper"},"relations":[],"meta":{"timestamp":"2016-08-07T09:51:49Z","version":2,"changeset":41301001,"user":"Parassrest","uid":3569249}},"geometry":{"type":"Point","coordinates":[83.9849902,28.2129917]}},{"type":"Feature","id":"node/4650716054","properties":{"type":"node","id":4650716054,"tags":{"name":"Samadhan Rasrta Dainik","name:ne":"समाधान राष्ट्र दैनिक","office":"newspaper","source":"2C_Pokhara Field Data Colletion"},"relations":[],"meta":{"timestamp":"2018-06-21T03:42:36Z","version":6,"changeset":60028413,"user":"Gaurav Thapa","uid":4212590}},"geometry":{"type":"Point","coordinates":[84.0567665,28.1628404]}},{"type":"Feature","id":"node/4789525324","properties":{"type":"node","id":4789525324,"tags":{"contact:phone":"9861183096","name":"Samadhan News Rastriya Dainik","office":"newspaper","operator:type":"private","source":"2cpokhara"},"relations":[],"meta":{"timestamp":"2018-04-16T09:29:32Z","version":2,"changeset":58131817,"user":"sandip parajuli","uid":7668145}},"geometry":{"type":"Point","coordinates":[84.0376375,28.1838811]}},{"type":"Feature","id":"node/4817293467","properties":{"type":"node","id":4817293467,"tags":{"name":"Adarsha Samaj Samparka Karyalaye","office":"newspaper"},"relations":[],"meta":{"timestamp":"2017-04-26T05:18:45Z","version":1,"changeset":48149688,"user":"Bishal9841","uid":3573216}},"geometry":{"type":"Point","coordinates":[84.0921647,28.115778]}},{"type":"Feature","id":"node/5234408623","properties":{"type":"node","id":5234408623,"tags":{"name":"Kaski Aawaj","office":"newspaper"},"relations":[],"meta":{"timestamp":"2018-03-28T04:11:53Z","version":2,"changeset":57586527,"user":"Ro Sun","uid":3112087}},"geometry":{"type":"Point","coordinates":[83.9898298,28.2260833]}},{"type":"Feature","id":"node/5431594939","properties":{"type":"node","id":5431594939,"tags":{"name":"Adarsha Samaj Contact Office","office":"newspaper"},"relations":[],"meta":{"timestamp":"2018-06-21T03:41:41Z","version":2,"changeset":60028403,"user":"Gaurav Thapa","uid":4212590}},"geometry":{"type":"Point","coordinates":[83.9362818,28.2780322]}},{"type":"Feature","id":"node/5508848768","properties":{"type":"node","id":5508848768,"tags":{"name":"Annapurna Post","office":"newspaper","source":"2cpokhara"},"relations":[],"meta":{"timestamp":"2018-06-21T05:10:46Z","version":2,"changeset":60029944,"user":"Ro Sun","uid":3112087}},"geometry":{"type":"Point","coordinates":[83.9856924,28.2136156]}},{"type":"Feature","id":"node/5543097207","properties":{"type":"node","id":5543097207,"tags":{"contact:phone":"061-526668","name":"Samadhan Paper","office":"newspaper","source":"2cpokhara"},"relations":[],"meta":{"timestamp":"2018-04-10T14:50:56Z","version":1,"changeset":57975078,"user":"Active Asmita","uid":7644107}},"geometry":{"type":"Point","coordinates":[83.9892626,28.2165688]}},{"type":"Feature","id":"node/5578045426","properties":{"type":"node","id":5578045426,"tags":{"contact:email":"adarsamaj@gmail.com","contact:phone":"061-531200, 061-521484","name":"Adarsha Samaj National Daily","office":"newspaper","source":"2c peset"},"relations":[],"meta":{"timestamp":"2018-04-25T09:26:56Z","version":1,"changeset":58402131,"user":"sadeepta dh","uid":4851333}},"geometry":{"type":"Point","coordinates":[83.9848179,28.2130556]}},{"type":"Feature","id":"node/5707199737","properties":{"type":"node","id":5707199737,"tags":{"name":"Pokhara Aawaj","office":"newspaper","phone":"061-523555"},"relations":[],"meta":{"timestamp":"2018-06-21T05:10:46Z","version":1,"changeset":60029944,"user":"Ro Sun","uid":3112087}},"geometry":{"type":"Point","coordinates":[83.9909586,28.2267597]}},{"type":"Feature","id":"node/5707344137","properties":{"type":"node","id":5707344137,"tags":{"name":"Pokhara Hotline","office":"newspaper"},"relations":[],"meta":{"timestamp":"2018-06-21T06:03:28Z","version":1,"changeset":60031146,"user":"Ro Sun","uid":3112087}},"geometry":{"type":"Point","coordinates":[83.985959,28.2122602]}}],"createdOn":1529990500956}